cbci_mcp/__init__.py
cbci_mcp/client.py
cbci_mcp/server.py
cbci_mcp-1.0.0.dist-info/METADATA
cbci_mcp-1.0.0.dist-info/WHEEL
cbci_mcp-1.0.0.dist-info/top_level.txt
cbci_mcp-1.0.0.dist-info/RECORD
