Metadata-Version: 2.4
Name: cbci-mcp
Version: 1.0.0
Summary: CBCI MCP (Model Context Protocol) - ChatBot CI with Dynamic Database Querying
Author-email: CBCI MCP Team <rosci671233@gmail.com>
License: MIT
Project-URL: Homepage, https://github.com/your-username/cbci-mcp
Project-URL: Repository, https://github.com/your-username/cbci-mcp
Project-URL: Issues, https://github.com/your-username/cbci-mcp/issues
Classifier: Development Status :: 4 - Beta
Classifier: Intended Audience :: Developers
Classifier: License :: OSI Approved :: MIT License
Classifier: Programming Language :: Python :: 3
Classifier: Programming Language :: Python :: 3.9
Classifier: Programming Language :: Python :: 3.10
Classifier: Programming Language :: Python :: 3.11
Classifier: Programming Language :: Python :: 3.12
Classifier: Topic :: Scientific/Engineering :: Artificial Intelligence
Classifier: Topic :: Software Development :: Libraries :: Python Modules
Classifier: Topic :: Communications :: Chat
Classifier: Topic :: Database
Requires-Python: >=3.9
Requires-Dist: openai>=1.0.0
Requires-Dist: pandas>=1.5.0
Requires-Dist: pyyaml>=6.0
Requires-Dist: ibm-db>=3.1.0
